{"code_big-files-upload_index.md":"CzOSCfcN","code_chat_readme.md":"kX9MlFWP","code_fe-rec_readme.md":"DqGGPzXj","code_virtual-list_readme.md":"Dq5rxPhN","code_web3_readme.md":"CPlSkbPv","index.md":"CDjxOwYL","pages_blockchain_blockchainbase.md":"DyhjIdkw","pages_blockchain_ethereum.md":"PVnbrKX0","pages_blockchain_loan.md":"O92p3B0-","pages_blockchain_solidity.md":"Df8L_G0p","pages_blockchain_staking.md":"DxBpq4IN","pages_blockchain_swap.md":"Dl1MUI15","pages_datastructure.md":"RRTQ0zDi","pages_designpatterns.md":"BdPIdEH9","pages_flutter_component.md":"nv1BmEA4","pages_flutter_dart.md":"zLfIYvrS","pages_flutter_dio.md":"BPB2uc5u","pages_git.md":"BIMqzKLR","pages_guide.md":"qkQM-G2F","pages_htmlcss_align.md":"B713h487","pages_htmlcss_bfc.md":"BY4RYvVj","pages_htmlcss_boxmodel.md":"CB_FnBC7","pages_htmlcss_cssframework.md":"DiDgyc09","pages_htmlcss_dice.md":"IpMV0yBp","pages_htmlcss_grid.md":"DSvRCH4v","pages_htmlcss_htmlcss.md":"BTfPXtS7","pages_htmlcss_layout.md":"Br8WOAwm","pages_htmlcss_margin.md":"Ap7VT8rT","pages_htmlcss_position.md":"B3Ozv9dU","pages_htmlcss_rem-em-vw.md":"B9UuNbS2","pages_http.md":"D1vxIOfi","pages_jsbase_arrayapi.md":"BytUxdDY","pages_jsbase_binary.md":"BlHrAx8t","pages_jsbase_coding.md":"DzxYlXBD","pages_jsbase_cookielocal.md":"C9st3LNd","pages_jsbase_datatype.md":"BA0IaKxO","pages_jsbase_eightleggedessay.md":"B9L118qG","pages_jsbase_eventloop.md":"C8mBviuZ","pages_jsbase_promise.md":"SIuXqMBX","pages_jsbase_promotion.md":"CCGyEr-B","pages_jsbase_prototype.md":"CdTFUIr9","pages_jsbase_regular.md":"BWRWNuxi","pages_jsbase_scope.md":"BGe1H7tI","pages_jsbase_this.md":"Cpknh-kc","pages_jsbase_typeconversion.md":"ClSxFGvq","pages_jsbase_typescript.md":"DRtXFsLf","pages_leetcode.md":"DVYQVaaM","pages_linux.md":"CTRqPCgb","pages_micro.md":"GMe08LWh","pages_nginx.md":"BJcmpeRG","pages_nodejs_index.md":"D0rb1BqU","pages_nodejs_nest.md":"BIJaa0Vz","pages_react_react.md":"Dmj1CB9S","pages_react_redux.md":"CP7Lzw0t","pages_serverside_database.md":"DVtu6H3U","pages_serverside_docker.md":"CI1dVtM2","pages_serverside_gateway.md":"EEcWERHC","pages_serverside_javase.md":"_NMhFcC7","pages_serverside_maven.md":"DamsIyfl","pages_serverside_mybatis.md":"B56_ePgU","pages_serverside_mybatisplus.md":"DSXgDGVw","pages_serverside_rabbitmq.md":"DhXEnhrx","pages_serverside_redis.md":"3tPUiGvb","pages_serverside_sentinel.md":"DggNQJRI","pages_serverside_spring.md":"DpICzrLO","pages_serverside_springboot.md":"Du1Zo2BQ","pages_serverside_springcloud.md":"CivF21uF","pages_serverside_springmvc.md":"BGjIrley","pages_ssr.md":"C_eaJV0R","pages_timezone.md":"BtJNrlGU","pages_updatelog.md":"Dk38yknW","pages_vue_vue2.0.md":"Dw9J_H0R","pages_vue_vue3.0.md":"DjlhrEcq","pages_vue_vuerouter4.0.md":"Cq0ob3sD","pages_vue_vuex4.0.md":"PhuCSfDr","pages_webpack.md":"Cd2giKJc","pages_webpackvite.md":"TMy9qdTO","pages_whistle.md":"K-GPS70i","pages_workreview_audio.md":"DKtzRbqh","pages_workreview_axiospackaging.md":"hQXLW3AP","pages_workreview_babelplugins.md":"bSlfsvqq","pages_workreview_bigfileupload.md":"DonfUZw9","pages_workreview_eslintplugins.md":"CFD4ABRo","pages_workreview_imagecroppingcompression.md":"OGq7RA6t","pages_workreview_imagedragverification.md":"Cqa7kPNd","pages_workreview_interfacesignaturedesign.md":"Mn3XBzQH","pages_workreview_monitor.md":"CD14EE7D","pages_workreview_optimize.md":"CSlj2PI9","pages_workreview_reactsolt.md":"CB0sfQ9c","pages_workreview_reduxpersistence.md":"B_r-RCsw","pages_workreview_stripe.md":"CtwOxZTZ","pages_workreview_virtuallist.md":"PVY5Gy7A","pages_workreview_vuexpersistence.md":"D6RqRq1r","pages_xss-csrf.md":"BNAtD-kg","readme.md":"DOnOoyck"}
